pyflinks/__init__.py
pyflinks/baseapi.py
pyflinks/client.py
pyflinks/exceptions.py
pyflinks/py.typed
pyflinks/entities/__init__.py
pyflinks/entities/attributes.py
pyflinks/entities/banking_services.py
pyflinks/entities/categorization.py
pyflinks-0.1.2.dist-info/LICENSE
pyflinks-0.1.2.dist-info/METADATA
pyflinks-0.1.2.dist-info/WHEEL
pyflinks-0.1.2.dist-info/top_level.txt
pyflinks-0.1.2.dist-info/RECORD
