Metadata-Version: 2.1
Name: pyflinks
Version: 0.1.2
Summary: A Python module for communicating with the Flinks.io API.
Home-page: https://github.com/agmoss/pyflinks
Author: Andrew Moss
Author-email: andrew@m0ss.dev
License: MIT
Keywords: flinks bank financial data institution
Classifier: Development Status :: 3 - Alpha
Classifier: Environment :: Web Environment
Classifier: Intended Audience :: Developers
Classifier: License :: OSI Approved :: MIT License
Classifier: Natural Language :: English
Classifier: Programming Language :: Python
Classifier: Programming Language :: Python :: 3
Classifier: Programming Language :: Python :: 3.11
License-File: LICENSE
Requires-Dist: requests >=2.0
